{"data":[{"name":"gv-theme","css":[{"name":"--gv-theme-color-darker","description":"Primary darker color","type":"color","default":"#1D3730","value":"#1D3730"},{"name":"--gv-theme-color-dark","description":"Primary dark color","type":"color","default":"#193E34","value":"#193E34"},{"name":"--gv-theme-color","description":"Primary color","type":"color","default":"#009B5B","value":"#009B5B"},{"name":"--gv-theme-color-light","description":"Primary light color","type":"color","default":"#D5FDCB","value":"#D5FDCB"},{"name":"--gv-theme-neutral-color-darkest","description":"Neutral darkest color","type":"color","default":"#000000","value":"#000000"},{"name":"--gv-theme-neutral-color-darker","description":"Neutral darker color","type":"color","default":"#BFBFBF","value":"#BFBFBF"},{"name":"--gv-theme-neutral-color-dark","description":"Neutral dark color","type":"color","default":"#D9D9D9","value":"#D9D9D9"},{"name":"--gv-theme-neutral-color","description":"Neutral color","type":"color","default":"#E5E5E5","value":"#E5E5E5"},{"name":"--gv-theme-neutral-color-light","description":"Neutral light color","type":"color","default":"#EFEFEF","value":"#EFEFEF"},{"name":"--gv-theme-neutral-color-lighter","description":"Neutral light color","type":"color","default":"#FAFAFA","value":"#FAFAFA"},{"name":"--gv-theme-neutral-color-lightest","description":"Neutral lightest color","type":"color","default":"#FFFFFF","value":"#FFFFFF"},{"name":"--gv-theme-font-color-dark","description":"Dark font color","type":"color","default":"#262626","value":"#262626"},{"name":"--gv-theme-font-color-light","description":"Light Font color","type":"color","default":"#FFFFFF","value":"#FFFFFF"},{"name":"--gv-theme-font-family","description":"Family","type":"string","default":"'IBM Plex Sans', 'Helvetica Neue', Arial, sans-serif","value":"'IBM Plex Sans', 'Helvetica Neue', Arial, sans-serif"},{"name":"--gv-theme-font-size-xs","description":"Extra small","type":"length","default":"10px","value":"10px"},{"name":"--gv-theme-font-size-s","description":"Small (Default)","type":"length","default":"12px","value":"12px"},{"name":"--gv-theme-font-size-m","description":"Medium","type":"length","default":"14px","value":"14px"},{"name":"--gv-theme-font-size-l","description":"Large","type":"length","default":"16px","value":"16px"},{"name":"--gv-theme-font-size-xl","description":"Extra large","type":"length","default":"26px","value":"26px"},{"name":"--gv-theme-font-size-xxl","description":"Extra extra large","type":"length","default":"30px","value":"30px"},{"name":"--gv-theme-skeleton-color","description":"Primary skeleton color","type":"color","default":"#BFBFBF","value":"#BFBFBF"}]},{"name":"gv-user-menu","css":[{"name":"--gv-user-menu--c","description":"Color","type":"color","default":"var(--gv-theme-font-color-dark, #262626)","value":""},{"name":"--gv-user-menu-hover--c","description":"Hover color","type":"color","default":"var(--gv-theme-color-dark, #193E34)","value":""},{"name":"--gv-user-menu--bgc","description":"Background color","type":"color","default":"transparent","value":"transparent"},{"name":"--gv-user-menu-list--bgc","description":"List background color","type":"color","default":"var(--gv-theme-neutral-color-lightest, #FFFFFF)","value":""},{"name":"--gv-user-menu-hover--bgc","description":"Hover background color","type":"color","default":"var(--gv-theme-color-light, #D5FDCB)","value":""},{"name":"--gv-user-menu--bdc","description":"Border color","type":"color","default":"lightgrey","value":"lightgrey"},{"name":"--gv-user-menu--tsh","description":"Text shadow","type":"string","default":"none","value":"none"},{"name":"--gv-user-menu-icon--c","description":"Icon color","type":"color","default":"var(--gv-theme-neutral-color-darkest, #000000)","value":""},{"name":"--gv-user-menu-icon--s","description":"Height and icon width","type":"length","default":"16px","value":"16px"},{"name":"--gv-user-menu-link-a--ph","description":"Link horizontal padding","type":"length","default":"0","value":"0"},{"name":"--gv-user-menu-link--ta","description":"Text align","type":"string","default":"right","value":"right"}]},{"name":"gv-pagination","css":[{"name":"--gv-pagination--fz","description":"Font size","type":"length","default":"var(--gv-theme-font-size-s, 12px)","value":""},{"name":"--gv-pagination-icon--s","description":"Height and icon width","type":"length","default":"18px","value":"18px"}]},{"name":"gv-menu","css":[{"name":"--gv-menu--c","description":"Color","type":"color","default":"var(--gv-theme-font-color-light, #FFFFFF)","value":""},{"name":"--gv-menu--bgc","description":"Background color.","type":"color","default":"var(--gv-theme-color-dark, #193E34)","value":""},{"name":"--gv-menu-link-active--bdbc","description":"Border bottom color of active link.","type":"color","default":"var(--gv-theme-color-light, #D5FDCB)","value":""},{"name":"--gv-menu-link-active--bdbs","description":"Border bottom style of active link.","type":"string","default":"solid","value":"solid"},{"name":"--gv-menu-link-active--bdbw","description":"Border bottom width of active link.","type":"length","default":"3px","value":"3px"},{"name":"--gv-menu-link-active--bgc","description":"Active background color","type":"color","default":"transparent","value":"transparent"},{"name":"--gv-menu-link--bgc","description":"Background color","type":"color","default":"transparent","value":"transparent"},{"name":"--gv-menu-link-a--pv","description":"Link vertical padding","type":"length","default":"0","value":"0"}]},{"name":"gv-header","css":[{"name":"--gv-header--bgc","description":"Background color.","type":"color","default":"var(--gv-theme-color-light, #D5FDCB)","value":""},{"name":"--gv-header--c","description":"Color","type":"color","default":"var(--gv-theme-font-color-dark, #262626)","value":""},{"name":"--gv-header-image--h","description":"Image height","type":"length","default":"125px","value":"125px"},{"name":"--gv-header-image--w","description":"Image width","type":"length","default":"125px","value":"125px"},{"name":"--gv-header--h","description":"Height","type":"length","default":"150px","value":"150px"},{"name":"--gv-header-button--p","description":"Button adding","type":"length","default":"10px 24px","value":"10px 24px"},{"name":"--gv-header-button--fz","description":"Button font size","type":"length","default":"var(--gv-theme-font-size-l, 16px)","value":""}]},{"name":"gv-tree","css":[{"name":"--gv-tree--bgc","description":"Background color","type":"color","default":"var(--gv-theme-neutral-color-lightest, #FFFFFF)","value":""},{"name":"--gv-tree--c","description":"Color","type":"color","default":"var(--gv-theme-font-color-dark, #262626)","value":""},{"name":"--gv-tree-active--bd","description":"Active border","type":"color","default":"var(--gv-theme-neutral-color-lightest, #FFFFFF)","value":""},{"name":"--gv-tree-active--bgc","description":"Active background color","type":"color","default":"var(--gv-theme-neutral-color-lighter, #FAFAFA)","value":""},{"name":"--gv-tree-hover--bgc","description":"Hover background color","type":"color","default":"var(--gv-theme-neutral-color-lightest, #FFFFFF)","value":""},{"name":"--gv-tree-link-a--ph","description":"Link horizontal padding","type":"length","default":"0","value":"0"},{"name":"--gv-tree-link--ta","description":"Text align","type":"string","default":"left","value":"left"},{"name":"--gv-tree-icon--s","description":"Height and icon width","type":"length","default":"20px","value":"20px"}]},{"name":"gv-table","css":[{"name":"--gv-table-selected--bgc","description":"Selected background color","type":"color","default":"var(--gv-theme-color, #009B5B)","value":""},{"name":"--gv-table-hover--bgc","description":"Row background color on hover","type":"color","default":"var(--gv-theme-neutral-color-lighter, #FAFAFA)","value":""},{"name":"--gv-table--bgc","description":"Background color","type":"color","default":"var(--gv-theme-neutral-color-lightest, #FFFFFF)","value":""},{"name":"--gv-table--bdc","description":"Border color","type":"color","default":"var(--gv-theme-neutral-color-dark, #D9D9D9)","value":""}]},{"name":"gv-stepper","css":[{"name":"--gv-stepper-validate--bgc","description":"Validate background color","type":"color","default":"var(--gv-theme-color, #009B5B)","value":""},{"name":"--gv-stepper-passed--bdc","description":"Passed border color","type":"color","default":"var(--gv-theme-color-light,#D5FDCB)","value":""},{"name":"--gv-stepper--bgc","description":"Background color","type":"color","default":"var(--gv-theme-neutral-color-dark, #BFBFBF)","value":""},{"name":"--gv-stepper--bdc","description":"Border color","type":"color","default":"var(--gv-theme-neutral-color-dark, #BFBFBF)","value":""},{"name":"--gv-stepper--c","description":"Color","type":"color","default":"var(--gv-theme-neutral-color-dark, #BFBFBF)","value":""},{"name":"--gv-stepper-passed--c","description":"Passed color","type":"color","default":"#595959","value":"#595959"},{"name":"--gv-stepper-icon--s","description":"Height and icon width","type":"length","default":"32px","value":"32px"}]},{"name":"gv-row","css":[{"name":"--gv-row--bgc","description":"Background color","type":"color","default":"var(--gv-theme-neutral-color-lightest, #FFFFFF)","value":""},{"name":"--gv-row-hover--bgc","description":"Background color when hover","type":"color","default":"var(--gv-theme-neutral-color-lighter, #FAFAFA)","value":""},{"name":"--gv-row-icon--s","description":"Height and icon width","type":"length","default":"14px","value":"14px"},{"name":"--gv-row-image--h","description":"Image height","type":"length","default":"35px","value":"35px"},{"name":"--gv-row-image--w","description":"Image width","type":"length","default":"35px","value":"35px"}]},{"name":"gv-rating","css":[{"name":"--gv-rating--c","description":"Color","type":"color","default":"var(--gv-theme-color, #009B5B)","value":""},{"name":"--gv-rating--s","description":"Size","type":"length","default":"13px","value":"13px"}]},{"name":"gv-rating-list","css":[{"name":"--gv-rating-list--bgc","description":"Background color","type":"color","default":"var(--gv-theme-neutral-color-lightest, #FFFFFF)","value":""},{"name":"--gv-rating-list-answer--bgc","description":"Answer background color","type":"color","default":"var(--gv-theme-neutral-color-lighter, #FAFAFA)","value":""},{"name":"--gv-rating-list--bdc","description":"Border color","type":"color","default":"var(--gv-theme-neutral-color, #E5E5E5)","value":""},{"name":"--gv-rating-list--s","description":"Height and star width","type":"length","default":"18px","value":"18px"}]},{"name":"gv-promote","css":[{"name":"--gv-promote-image--bgc","description":"Image background color","type":"color","default":"var(--gv-theme-color-light,#D5FDCB)","value":""},{"name":"--gv-promote--bgc","description":"Background color","type":"color","default":"var(--gv-theme-neutral-color-lightest, #FFFFFF)","value":""},{"name":"--gv-promote-image--h","description":"Image height","type":"length","default":"300px","value":"300px"},{"name":"--gv-promote-image--w","description":"Image width","type":"length","default":"300px","value":"300px"},{"name":"--gv-promote-button--p","description":"Button padding","type":"length","default":"19px 80px","value":"19px 80px"},{"name":"--gv-promote-button--fz","description":"Button font size","type":"length","default":"var(--gv-theme-font-size-l, 16px)","value":""}]},{"name":"gv-popover","css":[{"name":"--gv-popover--bgc","description":"Background color","type":"color","default":"var(--gv-theme-neutral-color-lighter, #FAFAFA)","value":""},{"name":"--gv-popover--bdc","description":"Border color","type":"color","default":"var(--gv-theme-neutral-color, #E5E5E5)","value":""},{"name":"--gv-popover--maw","description":"Max width","type":"length","default":"350px","value":"350px"}]},{"name":"gv-plans","css":[{"name":"--gv-plans--bgc","description":"Background color","type":"color","default":"var(--gv-theme-color, #009B5B)","value":""},{"name":"--gv-plans-font--c","description":"Font color","type":"color","default":"var(--gv-theme-font-color-light, #FFFFFF)","value":""},{"name":"--gv-plans-characteristic--bgc","description":"Characteristic background color","type":"color","default":"var(--gv-theme-color-light, #D5FDCB)","value":""},{"name":"--gv-plans-characteristics--bdc","description":"Characteristics border color","type":"color","default":"var(--gv-theme-neutral-color, #E5E5E5)","value":""},{"name":"--gv-plans-icon--s","description":"Height and icon width","type":"length","default":"24px","value":"24px"}]},{"name":"gv-option","css":[{"name":"--gv-option--bgc","description":"Background color","type":"color","default":"var(--gv-theme-neutral-color-dark, #BFBFBF)","value":""},{"name":"--gv-option--bdrs","description":"Border radius","type":"length","default":"0.15rem","value":"0.15rem"},{"name":"--gv-option-button--p","description":"Button padding","type":"length","default":"5px","value":"5px"}]},{"name":"gv-list","css":[{"name":"--gv-list--bgc","description":"Background color","type":"color","default":"var(--gv-theme-neutral-color-lightest, #FFFFFF)","value":""},{"name":"--gv-list-icon--s","description":"Height and icon width","type":"length","default":"20px","value":"20px"},{"name":"--gv-list-image--h","description":"Image height","type":"length","default":"40px","value":"40px"},{"name":"--gv-list-image--w","description":"Image width","type":"length","default":"40px","value":"40px"}]},{"name":"gv-info","css":[{"name":"--gv-info--bgc","description":"Background color","type":"color","default":"var(--gv-theme-neutral-color-lightest, #FFFFFF)","value":""},{"name":"--gv-info-rating--s","description":"Height and rating width","type":"length","default":"24px","value":"24px"},{"name":"--gv-info-image--h","description":"Image height","type":"length","default":"32px","value":"32px"},{"name":"--gv-info-image--w","description":"Image width","type":"length","default":"32px","value":"32px"}]},{"name":"gv-confirm","css":[{"name":"--gv-confirm--bgc","description":"Background color","type":"color","default":"var(--gv-theme-neutral-color-lighter, #FAFAFA)","value":""},{"name":"--gv-confirm--maw","description":"Max width","type":"length","default":"250px","value":"250px"}]},{"name":"gv-code","css":[{"name":"--gv-code--ff","description":"Font family","type":"string","default":"Operator Mono, Inconsolata, Roboto Mono, monaco, consolas, monospace","value":"Operator Mono, Inconsolata, Roboto Mono, monaco, consolas, monospace"},{"name":"--gv-code--fz","description":"Font size","type":"length","default":"var(--gv-theme-font-size-m, 14px)","value":""},{"name":"--gv-code--bgc","description":"Background color","type":"color","default":"var(--gv-theme-neutral-color-lighter, #FAFAFA)","value":""},{"name":"--gv-code--c","description":"Color","type":"color","default":"var(--gv-theme-font-color-dark, #262626)","value":""},{"name":"--gv-code--bdw","description":"Border width","type":"length","default":"1px","value":"1px"},{"name":"--gv-code--bds","description":"Border style","type":"string","default":"solid","value":"solid"},{"name":"--gv-code--bdc","description":"Border color","type":"color","default":"var(--gv-theme-color, #009B5B)","value":""},{"name":"--gv-code-icon--s","description":"Height and icon width","type":"length","default":"24px","value":"24px"}]},{"name":"gv-category","css":[{"name":"--gv-category--bgc","description":"Background color","type":"color","default":"var(--gv-theme-neutral-color-lightest, #FFFFFF)","value":""},{"name":"--gv-category--c","description":"Color","type":"color","default":"var(--gv-theme-font-color-dark, #262626)","value":""},{"name":"--gv-category--h","description":"Height","type":"length","default":"228px","value":"228px"}]},{"name":"gv-category-list","css":[{"name":"--gv-category-list--bgc-1","description":"Category background color 1","type":"color","default":"#CCE6EB","value":"#CCE6EB"},{"name":"--gv-category-list--bgc-2","description":"Category background color 2","type":"color","default":"#FCF1A8","value":"#FCF1A8"},{"name":"--gv-category-list--bgc-3","description":"Category background color 3","type":"color","default":"#D9D4F1","value":"#D9D4F1"},{"name":"--gv-category-list--bgc-4","description":"Category background color 4","type":"color","default":"#F9C15E","value":"#F9C15E"},{"name":"--gv-category-list--bgc-5","description":"Category background color 5","type":"color","default":"#D4FCCD","value":"#D4FCCD"},{"name":"--gv-category-list--bgc-6","description":"Category background color 6","type":"color","default":"#E0C8B2","value":"#E0C8B2"}]},{"name":"gv-card","css":[{"name":"--gv-card--bgc","description":"Background color","type":"color","default":"var(--gv-theme-neutral-color-lightest, #FFFFFF)","value":""},{"name":"--gv-card-image--h","description":"Image height","type":"length","default":"65px","value":"65px"},{"name":"--gv-card-image--w","description":"Image width","type":"length","default":"110px","value":"110px"}]},{"name":"gv-card-full","css":[{"name":"--gv-card-full--bgc","description":"Background color","type":"color","default":"var(--gv-theme-neutral-color-lightest, #FFFFFF)","value":""},{"name":"--gv-card-full-image--h","description":"Image height","type":"length","default":"65px","value":"65px"},{"name":"--gv-card-full-image--w","description":"Image width","type":"length","default":"110px","value":"110px"}]},{"name":"gv-text","css":[{"name":"--gv-input--bdc","description":"Border color","type":"color","default":"var(--gv-theme-neutral-color-dark, #D9D9D9)","value":""}]},{"name":"gv-tag","css":[{"name":"--gv-tag--bdr","description":"Border radius","type":"length","default":"4px","value":"4px"},{"name":"--gv-tag--bsw","description":"Box shadow","type":"string","default":"none","value":"none"},{"name":"--gv-tag--bgc","description":"Background color","type":"color","default":"var(--gv-theme-neutral-color-lighter, #FAFAFA)","value":""},{"name":"--gv-tag-major--bgc","description":"Major background color","type":"color","default":"var(--gv-theme-color, #009B5B)","value":""},{"name":"--gv-tag-minor--bgc","description":"Minor background color","type":"color","default":"var(--gv-theme-neutral-color-lightest, #FFFFFF)","value":""},{"name":"--gv-tag--bdc","description":"Border color","type":"color","default":"var(--gv-theme-neutral-color-dark, #D9D9D9)","value":""},{"name":"--gv-tag-major--bdc","description":"Major border color","type":"color","default":"var(--gv-theme-color, #009B5B)","value":""},{"name":"--gv-tag-minor--bdc","description":"Minor border color","type":"color","default":"var(--gv-theme-neutral-color-dark, #D9D9D9)","value":""},{"name":"--gv-tag--bds","description":"Border style","type":"string","default":"solid","value":"solid"},{"name":"--gv-tag-major--bds","description":"Major border style","type":"string","default":"solid","value":"solid"},{"name":"--gv-tag-minor--bds","description":"Minor border style","type":"string","default":"dashed","value":"dashed"},{"name":"--gv-tag--bdw","description":"Border width","type":"length","default":"1px","value":"1px"},{"name":"--gv-tag-major--bdw","description":"Major border width","type":"length","default":"1px","value":"1px"},{"name":"--gv-tag-minor--bdw","description":"Minor border width","type":"length","default":"1px","value":"1px"},{"name":"--gv-tag--c","description":"Color","type":"color","default":"var(--gv-theme-font-color-dark, #262626)","value":""},{"name":"--gv-tag-major--c","description":"Major color","type":"color","default":"var(--gv-theme-font-color-light, #FFFFFF)","value":""},{"name":"--gv-tag-minor--c","description":"Minor color","type":"color","default":"var(--gv-theme-font-color-dark, #262626)","value":""},{"name":"--gv-tag-icon--s","description":"Height and icon width","type":"length","default":"18px","value":"18px"}]},{"name":"gv-switch","css":[{"name":"--gv-switch-on--bgc","description":"On background color","type":"color","default":"var(--gv-theme-color, #009B5B)","value":""},{"name":"--gv-switch-off--bgc","description":"Off background color","type":"color","default":"var(--gv-theme-neutral-color-dark, #BFBFBF)","value":""},{"name":"--gv-switch--bgc","description":"Switch background color","type":"color","default":"var(--gv-theme-neutral-color-lightest, #FFFFFF)","value":""}]},{"name":"gv-state","css":[{"name":"--gv-state--bdr","description":"Border radius","type":"length","default":"17px","value":"17px"},{"name":"--gv-state--bgc","description":"Background color","type":"color","default":"#F0F5FF","value":"#F0F5FF"},{"name":"--gv-state--c","description":"Color","type":"color","default":"#597EF7","value":"#597EF7"},{"name":"--gv-state-major--bgc","description":"Major background color","type":"color","default":"var(--gv-theme-color-light, #D5FDCB)","value":""},{"name":"--gv-state-major--c","description":"Major color","type":"color","default":"var(--gv-theme-color, #009B5B)","value":""}]},{"name":"gv-select","css":[{"name":"--gv-select--bgc","description":"Background color","type":"color","default":"var(--gv-theme-neutral-color-lightest, #FFFFFF)","value":""},{"name":"--gv-select--bdc","description":"Border color","type":"color","default":"var(--gv-theme-neutral-color, #E5E5E5)","value":""},{"name":"--gv-select--c","description":"Color","type":"color","default":"var(--gv-theme-font-color-dark, #262626)","value":""},{"name":"--gv-select-hover--bgc","description":"Active background color","type":"color","default":"var(--gv-theme-color-light, #D5FDCB)","value":""},{"name":"--gv-select-selected--bgc","description":"Hover background color","type":"color","default":"var(--gv-theme-neutral-color-lighter, #FAFAFA)","value":""}]},{"name":"gv-metric","css":[{"name":"--gv-metric--c","description":"Color","type":"color","default":"var(--gv-theme-color, #009B5B)","value":""},{"name":"--gv-metric-icon--s","description":"Height and icon width","type":"length","default":"24px","value":"24px"}]},{"name":"gv-message","css":[{"name":"--gv-message-success--bgc","description":"Success background color","type":"color","default":"var(--gv-theme-color-light, #D5FDCB)","value":""},{"name":"--gv-message-success--c","description":"Success color","type":"color","default":"var(--gv-theme-color-darker, #1D3730)","value":""},{"name":"--gv-message-info--c","description":"Info color","type":"color","default":"#00529B","value":"#00529B"},{"name":"--gv-message-info--bgc","description":"Info background color","type":"color","default":"#BDE5F8","value":"#BDE5F8"},{"name":"--gv-message-warn--c","description":"Warning color","type":"color","default":"#9F6000","value":"#9F6000"},{"name":"--gv-message-warn--bgc","description":"Warning background color","type":"color","default":"#FEEFB3","value":"#FEEFB3"},{"name":"--gv-message-error--c","description":"Error color","type":"color","default":"#820014","value":"#820014"},{"name":"--gv-message-error--bgc","description":"Error background color","type":"color","default":"#FFCCC7","value":"#FFCCC7"}]},{"name":"gv-link","css":[{"name":"--gv-link-a--pv","description":"Vertical padding for the inner <a> tag","type":"length","default":"15px","value":"15px"},{"name":"--gv-link-a--ph","description":"Horizontal padding for the inner <a> tag","type":"length","default":"15px","value":"15px"},{"name":"--gv-link--c","description":"Color","type":"color","default":"var(--gv-theme-font-color-dark, #262626)","value":""},{"name":"--gv-link-active--c","description":"Active color","type":"color","default":"var(--gv-theme-font-color-light, #FFFFFF)","value":""},{"name":"--gv-link--bgc","description":"Background color","type":"color","default":"transparent","value":"transparent"},{"name":"--gv-link-active--bgc","description":"Active background color","type":"color","default":"var(--gv-theme-color-dark, #193E34)","value":""},{"name":"--gv-link-active--bdbc","description":"Active border bottom color","type":"color","default":"none","value":"none"},{"name":"--gv-link-active--bdbs","description":"Active border bottom style","type":"string","default":"none","value":"none"},{"name":"--gv-link-active--bdbw","description":"Active border bottom width","type":"length","default":"none","value":"none"},{"name":"--gv-link--ta","description":"Text align","type":"string","default":"center","value":"center"},{"name":"--gv-link--td","description":"Text decoration","type":"string","default":"none","value":"none"},{"name":"--gv-link--tsh","description":"Text shadow","type":"string","default":"none","value":"none"},{"name":"--gv-link-icon--s","description":"Height and icon width","type":"length","default":"24px","value":"24px"}]},{"name":"gv-input","css":[{"name":"--gv-input--bdc","description":"Border color","type":"color","default":"var(--gv-theme-neutral-color, #E5E5E5)","value":""}]},{"name":"gv-image","css":[{"name":"--gv-image--of","description":"set the object-fit of image","type":"string","default":"cover","value":"cover"}]},{"name":"gv-icon","css":[{"name":"--gv-icon--c","description":"Color","type":"color","default":"var(--gv-theme-font-color-dark,  #262626)","value":""},{"name":"--gv-icon--s","description":"Height and width","type":"length","default":"32px","value":"32px"}]},{"name":"gv-checkbox","css":[{"name":"--gv-checkbox--bgc","description":"Checked background color","type":"color","default":"var(--gv-theme-color, #009B5B)","value":""}]},{"name":"gv-button","css":[{"name":"--gv-button--bgc","description":"Background color","type":"color","default":"var(--gv-theme-color-dark, #193E34)","value":""},{"name":"--gv-button--c","description":"Color","type":"color","default":"var(--gv-theme-font-color-light, #FFFFFF)","value":""},{"name":"--gv-button-primary--c","description":"Primary color","type":"color","default":"var(--gv-theme-font-color-light, #FFFFFF)","value":""},{"name":"--gv-button-primary--bgc","description":"Primary background color","type":"color","default":"var(--gv-theme-color, #009B5B)","value":""},{"name":"--gv-button--p","description":"Padding","type":"length","default":"0rem 0.5rem","value":"0rem 0.5rem"},{"name":"--gv-button--fz","description":"Font size","type":"length","default":"var(--gv-theme-font-size-m, 14px)","value":""},{"name":"--gv-button--bdrs","description":"Border radius","type":"length","default":"0.15rem","value":"0.15rem"}]}]}